# BYTECODE JAVA

El bytecode Java se encuentra dentro del archivo de extensión .class y es el tipo de instrucciones que la máquina virtual Java (JVM) espera recibir para posteriormente ser compiladas a lenguaje de máquina mediante un compilador JIT a la hora de su ejecución. Usualmente es el resultado de utilizar un compilador del lenguaje de programación Java (como javac), pero puede ser generado desde otros compiladores.

Las instrucciones caen en las siguientes categorías:

* Mover de memoria a registros y viceversa (ej. aload_0, istore).
* Aritmética y lógica (ej. ladd, fcmpl).
* Conversión de tipos (ej. i2b, d2i).
* Creación y manipulación de objetos (ej. new, putfield).
* Manipulación de la pila de operandos (ej. swap, dup2).
* Control de flujo (ej. ifeq, goto).
* Invocación de métodos y retorno de estos (ej. invokespecial, areturn).

## Bytecode Structure
Each instruction in Java bytecode is one byte in length, which is where the term “bytecode” comes from. Some instructions are followed by additional bytes that provide operands for the instructions. The bytecode instructions are designed to be compact, and efficient, and operate on a stack-based architecture. This is in contrast to most physical CPU architectures, which are register-based.

#### Structure:

- **Opcode:** The first byte of each instruction is known as the opcode. This byte indicates the operation to be performed.
- **Operands:** Some instructions are followed by one or more bytes that act as operands. These operands can be indices, constants, or references that the instruction operates on.


### Bytecode and the Java Stack
Java bytecode operates on a stack-based architecture. This means that most bytecode operations involve pushing items onto a stack or popping them off. For example, an arithmetic operation like addition in bytecode involves popping the top two items off the stack, adding them, and then pushing the result back onto the stack.

Example: Dissecting Bytecode

```
int a = 5;
int b = 10;
int sum = a + b
```

When compiled, these lines of Java code are converted into a series of bytecode instructions that might look like the following when viewed through a tool like javap:

```
0: iconst_5
1: istore_1
2: bipush 10
4: istore_2
5: iload_1
6: iload_2
7: iadd
8: istore_3
```

iconst_5 - Pushes the integer value 5 onto the stack.
istore_1 - Stores the top integer (5) from the stack into the first local variable (a).
bipush 10 - Pushes the byte value 10 onto the stack.
istore_2 - Stores the top integer (10) from the stack into the second local variable (b).
iload_1 and iload_2 - Loads the integers a and b onto the stack.
iadd - Pops the two top integers off the stack, adds them, and pushes the result (sum) back onto the stack.
istore_3 - Stores the result from the stack into the third local variable (sum).


## Key Functions of the JVM
The JVM performs several vital functions in the execution of a Java program:

- **Bytecode Loading:** The JVM loads the compiled Java bytecode from the .class files. This loading process also involves checking the bytecode for format and structural integrity.
- **Bytecode Verification:** Before execution, the bytecode is verified to ensure it adheres to Java’s safety and security standards. This step checks for illegal code that can violate access rights and potentially harm the system.
- **Execution:** The JVM executes the bytecode. It can interpret the bytecode directly, converting each instruction into machine code as the program runs. Alternatively, modern JVM implementations use Just-In-Time (JIT) compilation, where the bytecode is compiled into native machine code for improved performance.
- **Memory Management:** The JVM manages memory allocation for Java objects and arrays. It also takes care of garbage collection, automatically freeing memory that is no longer in use.
Providing a Runtime Environment: The JVM offers a runtime environment that includes libraries and APIs necessary for Java applications. It also provides a runtime that handles tasks like threading, synchronization, and resource management.

## Tools and Libraries for Bytecode Manipulation
Several tools and libraries have been developed to assist with bytecode manipulation in Java:

- **ASM:** A low-level bytecode manipulation and analysis framework. ASM offers direct manipulation of bytecode, providing a means to analyze, create, and modify compiled Java classes.
- **Javassist:** A higher-level bytecode manipulation library that allows developers to work with bytecode using a more straightforward API compared to ASM. It’s particularly useful for dynamically modifying classes at runtime.
- **Byte Buddy:** A relatively newer library for creating and modifying Java classes during the runtime of a Java application. It combines ease of use with powerful features, allowing developers to intercept method calls, create proxy classes, and more.

## Risks and Considerations
While bytecode manipulation offers powerful capabilities, it also comes with risks and considerations:

- **Complexity:** Manipulating bytecode is more complex and error-prone than working with Java source code.
- **Maintainability:** Changes made at the bytecode level can be hard to track and maintain, especially for those unfamiliar with bytecode structure.
- **Compatibility:** Bytecode changes can potentially break compatibility with future versions of the Java platform if not done carefully.